onnxruntime_azure.libs/libselinux-ae24b712.so.1
onnxruntime_azure.libs/libkeyutils-19c64d08.so.1.5
onnxruntime_azure.libs/libkrb5support-73f3f43d.so.0.1
onnxruntime_azure.libs/libgssapi_krb5-fec99a71.so.2.2
onnxruntime_azure.libs/libcrypto-13880bfc.so.1.0.2k
onnxruntime_azure.libs/libcom_err-057ba42b.so.2.1
onnxruntime_azure.libs/libkrb5-90a0ef7c.so.3.3
onnxruntime_azure.libs/libpcre-6b975b27.so.1.2.0
onnxruntime_azure.libs/libk5crypto-47ac5e52.so.3.1
onnxruntime_azure.libs/libssl-e50c59ab.so.1.0.2k
onnxruntime_azure-1.15.0.dist-info/top_level.txt
onnxruntime_azure-1.15.0.dist-info/RECORD
onnxruntime_azure-1.15.0.dist-info/WHEEL
onnxruntime_azure-1.15.0.dist-info/entry_points.txt
onnxruntime_azure-1.15.0.dist-info/METADATA
onnxruntime/ThirdPartyNotices.txt
onnxruntime/LICENSE
onnxruntime/Privacy.md
onnxruntime/__init__.py
onnxruntime/transformers/fusion_nhwc_conv.py
onnxruntime/transformers/huggingface_models.py
onnxruntime/transformers/onnx_model_bart.py
onnxruntime/transformers/fusion_gelu_approximation.py
onnxruntime/transformers/benchmark_helper.py
onnxruntime/transformers/benchmark.py
onnxruntime/transformers/fusion_gelu.py
onnxruntime/transformers/onnx_model_gpt2.py
onnxruntime/transformers/float16.py
onnxruntime/transformers/fusion_qordered_matmul.py
onnxruntime/transformers/fusion_biasgelu.py
onnxruntime/transformers/fusion_utils.py
onnxruntime/transformers/io_binding_helper.py
onnxruntime/transformers/profiler.py
onnxruntime/transformers/fusion_attention.py
onnxruntime/transformers/fusion_qordered_gelu.py
onnxruntime/transformers/onnx_model_t5.py
onnxruntime/transformers/quantize_helper.py
onnxruntime/transformers/fusion_fastgelu.py
onnxruntime/transformers/fusion_options.py
onnxruntime/transformers/fusion_qordered_layernorm.py
onnxruntime/transformers/fusion_skiplayernorm.py
onnxruntime/transformers/fusion_transpose.py
onnxruntime/transformers/compare_bert_results.py
onnxruntime/transformers/convert_tf_models_to_pytorch.py
onnxruntime/transformers/fusion_gemmfastgelu.py
onnxruntime/transformers/machine_info.py
onnxruntime/transformers/fusion_attention_vae.py
onnxruntime/transformers/torch_onnx_export_helper.py
